LICENSE.txt
MANIFEST.in
README.rst
setup.cfg
setup.py
tgapp_tgcomments.egg-info/PKG-INFO
tgapp_tgcomments.egg-info/SOURCES.txt
tgapp_tgcomments.egg-info/dependency_links.txt
tgapp_tgcomments.egg-info/entry_points.txt
tgapp_tgcomments.egg-info/not-zip-safe
tgapp_tgcomments.egg-info/requires.txt
tgapp_tgcomments.egg-info/top_level.txt
tgcomments/__init__.py
tgcomments/bootstrap.py
tgcomments/helpers.py
tgcomments/partials.py
tgcomments/controllers/__init__.py
tgcomments/controllers/root.py
tgcomments/lib/__init__.py
tgcomments/model/__init__.py
tgcomments/model/ming/__init__.py
tgcomments/model/ming/models.py
tgcomments/model/sqla/__init__.py
tgcomments/model/sqla/models.py
tgcomments/public/__init__.py
tgcomments/public/css/style.css
tgcomments/public/images/hide.gif
tgcomments/public/images/trash.gif
tgcomments/templates/__init__.py
tgcomments/templates/comments_partial.html
tgcomments/templates/comments_partial.xhtml