Metadata-Version: 2.1
Name: tgapp-tgcomments
Version: 0.2.6
Summary: TurboGears2 pluggable application for comments to entities with facebook sharing
Home-page: https://github.com/axant/tgapp-tgcomments
Author: Alessandro Molina, Vincenzo Castiglia
Author-email: alessandro.molina@axant.it, vincenzo.castiglia@axant.it
License: UNKNOWN
Keywords: turbogears2.application
Platform: UNKNOWN
License-File: LICENSE.txt
